ml_django_brain/__init__.py
ml_django_brain/admin.py
ml_django_brain/apps.py
ml_django_brain/middleware.py
ml_django_brain/models.py
ml_django_brain/registry.py
ml_django_brain/serializers.py
ml_django_brain/services.py
ml_django_brain/settings.py
ml_django_brain/signals.py
ml_django_brain/urls.py
ml_django_brain/views.py
ml_django_brain/management/__init__.py
ml_django_brain/management/commands/__init__.py
ml_django_brain/management/commands/evaluate_model.py
ml_django_brain/management/commands/list_models.py
ml_django_brain/management/commands/register_model.py
ml_django_brain/migrations/0001_initial.py
ml_django_brain/migrations/__init__.py
ml_django_brain/utils/__init__.py
ml_django_brain/utils/loaders.py
ml_django_brain/utils/metrics.py
ml_django_brain/utils/serialization.py
ml_django_brain-0.1.0.dist-info/licenses/LICENSE
ml_django_brain-0.1.0.dist-info/METADATA
ml_django_brain-0.1.0.dist-info/WHEEL
ml_django_brain-0.1.0.dist-info/top_level.txt
ml_django_brain-0.1.0.dist-info/RECORD
