Metadata-Version: 2.4
Name: ml-django-brain
Version: 0.1.0
Summary: A Django plugin for AI/ML integration with model registry, API generation, and monitoring
Home-page: https://github.com/sgh370/ml-django-brain
Author: Saeed Ghanbari
Author-email: sgh370@yahoo.com
License: MIT License
Project-URL: Documentation, https://github.com/sgh370/ml-django-brain
Project-URL: Bug Reports, https://github.com/sgh370/ml-django-brain/issues
Project-URL: Source, https://github.com/sgh370/ml-django-brain
Keywords: django,machine learning,ml,ai,model registry,api,monitoring
Classifier: Environment :: Web Environment
Classifier: Framework :: Django
Classifier: Framework :: Django :: 3.2
Classifier: Framework :: Django :: 4.0
Classifier: Framework :: Django :: 4.1
Classifier: Framework :: Django :: 4.2
Classifier: Intended Audience :: Developers
Classifier: Intended Audience :: Science/Research
Classifier: License :: OSI Approved :: MIT License
Classifier: Operating System :: OS Independent
Classifier: Programming Language :: Python
Classifier: Programming Language :: Python :: 3
Classifier: Programming Language :: Python :: 3.8
Classifier: Programming Language :: Python :: 3.9
Classifier: Programming Language :: Python :: 3.10
Classifier: Programming Language :: Python :: 3.11
Classifier: Programming Language :: Python :: 3.12
Classifier: Topic :: Internet :: WWW/HTTP
Classifier: Topic :: Internet :: WWW/HTTP :: Dynamic Content
Classifier: Topic :: Scientific/Engineering :: Artificial Intelligence
Classifier: Topic :: Software Development :: Libraries :: Python Modules
Requires-Python: >=3.8
License-File: LICENSE
Requires-Dist: Django>=3.2
Requires-Dist: djangorestframework>=3.12.0
Requires-Dist: numpy>=1.19.0
Requires-Dist: pandas>=1.1.0
Requires-Dist: scikit-learn>=0.24.0
Requires-Dist: joblib>=1.0.0
Requires-Dist: pyyaml>=5.4.0
Requires-Dist: jsonschema>=3.2.0
Dynamic: author
Dynamic: author-email
Dynamic: classifier
Dynamic: description
Dynamic: description-content-type
Dynamic: home-page
Dynamic: keywords
Dynamic: license
Dynamic: license-file
Dynamic: project-url
Dynamic: requires-dist
Dynamic: requires-python
Dynamic: summary
